odoo9_addon_product_supplierinfo_revision-9.0.1.0.0.99.dev4-py2.7-nspkg.pth
odoo9_addon_product_supplierinfo_revision-9.0.1.0.0.99.dev4.dist-info/DESCRIPTION.rst
odoo9_addon_product_supplierinfo_revision-9.0.1.0.0.99.dev4.dist-info/METADATA
odoo9_addon_product_supplierinfo_revision-9.0.1.0.0.99.dev4.dist-info/RECORD
odoo9_addon_product_supplierinfo_revision-9.0.1.0.0.99.dev4.dist-info/WHEEL
odoo9_addon_product_supplierinfo_revision-9.0.1.0.0.99.dev4.dist-info/metadata.json
odoo9_addon_product_supplierinfo_revision-9.0.1.0.0.99.dev4.dist-info/namespace_packages.txt
odoo9_addon_product_supplierinfo_revision-9.0.1.0.0.99.dev4.dist-info/top_level.txt
odoo_addons/product_supplierinfo_revision/README.rst
odoo_addons/product_supplierinfo_revision/__init__.py
odoo_addons/product_supplierinfo_revision/__openerp__.py
odoo_addons/product_supplierinfo_revision/i18n/es.po
odoo_addons/product_supplierinfo_revision/i18n/fr.po
odoo_addons/product_supplierinfo_revision/i18n/product_supplierinfo_revision.pot
odoo_addons/product_supplierinfo_revision/models/__init__.py
odoo_addons/product_supplierinfo_revision/models/product_supplierinfo.py
odoo_addons/product_supplierinfo_revision/static/description/icon.png
odoo_addons/product_supplierinfo_revision/tests/__init__.py
odoo_addons/product_supplierinfo_revision/tests/test_product_supplierinfo_revision.py
odoo_addons/product_supplierinfo_revision/views/product_supplierinfo_view.xml
odoo_addons/product_supplierinfo_revision/wizards/__init__.py
odoo_addons/product_supplierinfo_revision/wizards/supplierinfo_duplicate_wizard.py
odoo_addons/product_supplierinfo_revision/wizards/supplierinfo_duplicate_wizard_view.xml
